banking_api_shared/__init__.py
banking_api_shared/constants.py
banking_api_shared-0.1.2.dist-info/METADATA
banking_api_shared-0.1.2.dist-info/WHEEL
banking_api_shared-0.1.2.dist-info/top_level.txt
banking_api_shared-0.1.2.dist-info/RECORD
