Metadata-Version: 2.1
Name: banking-api-shared
Version: 0.1.2
Summary: Shared extensions for banking_api project
Home-page: https://github.com/edazizovv/oaiv
Download-URL: https://github.com/edazizovv/oaiv
Maintainer: Edward Azizov
Maintainer-email: edazizovv@gmail.com
License: Proprietary
Requires-Python: >=3.10
